SparkConf/__init__.py
SparkConf-0.1.dist-info/LICENSE.txt
SparkConf-0.1.dist-info/METADATA
SparkConf-0.1.dist-info/WHEEL
SparkConf-0.1.dist-info/top_level.txt
SparkConf-0.1.dist-info/RECORD
