Metadata-Version: 2.1
Name: SparkConf
Version: 0.1
Summary: This module generates spark config parameters for databricks cluster
Author: Sourav Bhattacharya
Author-email: Sourav.Bhattacharya@nike.com
Classifier: Programming Language :: Python :: 3
Classifier: License :: OSI Approved :: MIT License
Classifier: Operating System :: OS Independent
License-File: LICENSE.txt
